admin_email_sender/__init__.py
admin_email_sender/admin.py
admin_email_sender/apps.py
admin_email_sender/helpers.py
admin_email_sender/models.py
admin_email_sender/signals.py
admin_email_sender/utils.py
admin_email_sender/validators.py
admin_email_sender/views.py
admin_email_sender/migrations/0001_initial.py
admin_email_sender/migrations/0002_template.py
admin_email_sender/migrations/__init__.py
admin_email_sender/tests/__init__.py
admin_email_sender/tests/test_models.py
admin_email_sender/tests/test_validators.py
django_admin_email_sender-0.1.1.dist-info/DESCRIPTION.rst
django_admin_email_sender-0.1.1.dist-info/METADATA
django_admin_email_sender-0.1.1.dist-info/RECORD
django_admin_email_sender-0.1.1.dist-info/WHEEL
django_admin_email_sender-0.1.1.dist-info/metadata.json
django_admin_email_sender-0.1.1.dist-info/top_level.txt
