Metadata-Version: 2.0
Name: django-admin-email-sender
Version: 0.1.1
Summary: Django Admin Email Sender
Home-page: https://github.com/stasfilin/django-admin-email-sender.git
Author: https://github.com/stasfilin
Author-email: stasfilinmusic@gmail.com
License: Apache 2.0
Keywords: django,sender,django-admin-email-sender,admin,email
Platform: UNKNOWN
Classifier: Development Status :: 4 - Beta
Classifier: Intended Audience :: Developers
Classifier: Topic :: Software Development :: Libraries :: Python Modules
Classifier: Environment :: Web Environment
Classifier: Framework :: Django
Classifier: Topic :: Internet
Classifier: Programming Language :: Python
Classifier: Programming Language :: Python :: 3.5
Classifier: Programming Language :: Python :: 3.6
Classifier: Framework :: Django
